slosh/__init__.py
slosh/main.py
slosh-0.0.1.dist-info/LICENSE
slosh-0.0.1.dist-info/METADATA
slosh-0.0.1.dist-info/WHEEL
slosh-0.0.1.dist-info/entry_points.txt
slosh-0.0.1.dist-info/top_level.txt
slosh-0.0.1.dist-info/RECORD
