Metadata-Version: 2.1
Name: slosh
Version: 0.0.1
Summary: A wrapper around ssh that can save connections to your ssh config file.
Author: Emile Indik
Project-URL: Homepage, https://github.com/emileindik/slosh
Project-URL: Issues, https://github.com/emileindik/slosh/issues
Keywords: ssh,config,file
Classifier: Programming Language :: Python :: 3
Classifier: License :: OSI Approved :: MIT License
Classifier: Operating System :: OS Independent
License-File: LICENSE
